heisenberg/__init__.py
heisenberg/__main__.py
heisenberg/config.py
heisenberg/exceptions.py
heisenberg/server.py
heisenberg/utils.py
heisenberg_mcp_server-0.3.0.dist-info/METADATA
heisenberg_mcp_server-0.3.0.dist-info/WHEEL
heisenberg_mcp_server-0.3.0.dist-info/entry_points.txt
heisenberg_mcp_server-0.3.0.dist-info/top_level.txt
heisenberg_mcp_server-0.3.0.dist-info/RECORD
