Metadata-Version: 2.4
Name: heisenberg-mcp-server
Version: 0.3.0
Summary: A Model Context Protocol server that enables capable LLMs to work with Heisenberg features, such as inference
Author-email: SeshatLabs <info@seshatlabs.xyz>
Requires-Python: >=3.12
Requires-Dist: mcp<2.0.0,>=1.9.2
Requires-Dist: httpx<1.0.0,>=0.27.0
Requires-Dist: python-decouple>=3.8
Provides-Extra: dev
Requires-Dist: pytest<9.0.0,>=8.4.0; extra == "dev"
